darksheep_imap/__init__.py
darksheep_imap/_version.py
darksheep_imap/consts.py
darksheep_imap/errors.py
darksheep_imap/folder.py
darksheep_imap/idle.py
darksheep_imap/imap_utf7.py
darksheep_imap/mailbox.py
darksheep_imap/message.py
darksheep_imap/query.py
darksheep_imap/utils.py
darksheep_imap/extension/__init__.py
darksheep_imap/extension/imaplib.py
darksheep_imap-0.0.2.dist-info/METADATA
darksheep_imap-0.0.2.dist-info/WHEEL
darksheep_imap-0.0.2.dist-info/top_level.txt
darksheep_imap-0.0.2.dist-info/RECORD
