Metadata-Version: 2.1
Name: darksheep-imap
Version: 0.0.2
Summary: Dark sheep's imap
Home-page: UNKNOWN
Author: Dark Sheep
License: UNKNOWN
Platform: UNKNOWN
Classifier: Programming Language :: Python :: 3.6
Classifier: Programming Language :: Python :: 3.7
Classifier: Programming Language :: Python :: 3.8
Classifier: License :: OSI Approved :: MIT License
Classifier: Operating System :: OS Independent
Requires-Python: >=3.6
